nacos_py/__init__.py
nacos_py/client.py
nacos_py/commons.py
nacos_py/exception.py
nacos_py/files.py
nacos_py/listener.py
nacos_py/nacos.py
nacos_py/params.py
nacos_py/timer.py
nacos_py-0.1.3.dist-info/LICENSE
nacos_py-0.1.3.dist-info/METADATA
nacos_py-0.1.3.dist-info/WHEEL
nacos_py-0.1.3.dist-info/top_level.txt
nacos_py-0.1.3.dist-info/RECORD
