Metadata-Version: 2.1
Name: nacos-py
Version: 0.1.3
Summary: Python client for Nacos. 
Home-page: https://github.com/arckalsun/nacos-py
Author: arckal
Author-email: arckalsun@gmail.com
License: Apache License 2.0
Project-URL: Documentation, https://github.com/arckalsun/nacos-py
Project-URL: Source, https://github.com/arckalsun/nacos-py
Project-URL: Nacos Open API Guide, https://nacos.io/en-us/docs/open-api.html
Keywords: nacos-py,nacos-sdk-python
Platform: UNKNOWN
Classifier: Topic :: Software Development :: Libraries :: Python Modules
Classifier: Operating System :: OS Independent
Classifier: Programming Language :: Python
Classifier: Programming Language :: Python :: 2.7
Classifier: Programming Language :: Python :: 3.6
Classifier: Programming Language :: Python :: 3.7
